{"cameraMode":{"drawMode":0,"name":"Shaded","section":"Shading Mode"},"sceneLighting":true,"audioPlay":false,"sceneViewState":{"showFog":true,"showMaterialUpdate":false,"showSkybox":true,"showFlares":true,"showImageEffects":true,"showParticleSystems":true},"in2DMode":false,"pivot":{"x":0.02639627456665039,"y":1.1614172458648682,"z":-0.6948361396789551},"rotation":{"x":-0.05937524884939194,"y":0.9209113717079163,"z":-0.15505772829055787,"w":-0.35263851284980776},"size":11.411661148071289,"orthographic":false}